pyko/__init__.py
pyko/reader.py
pyko/tokenizer.py
pyko/tokenizer/__init__.py
pyko-0.4.3.dist-info/METADATA
pyko-0.4.3.dist-info/WHEEL
pyko-0.4.3.dist-info/top_level.txt
pyko-0.4.3.dist-info/RECORD
