Metadata-Version: 2.1
Name: pyko
Version: 0.4.3
Summary: Korean Text Processor
Home-page: https://github.com/codebasic/pyko
Author: Lee Seongjoo
Author-email: seongjoo@codebasic.io
License: UNKNOWN
Keywords: natural language processing text korean
Platform: UNKNOWN
Classifier: Programming Language :: Python :: 3 :: Only
Classifier: Natural Language :: Korean
Classifier: Operating System :: POSIX :: Linux
Classifier: Operating System :: MacOS :: MacOS X
Requires-Python: >=3.4
Requires-Dist: beautifulsoup4
Requires-Dist: lxml
Requires-Dist: nltk
